pynigiri/__init__.py
pynigiri/pynigiri.cpython-311-x86_64-linux-gnu.so
pynigiri-0.1.5.dist-info/WHEEL
pynigiri-0.1.5.dist-info/METADATA
pynigiri-0.1.5.dist-info/RECORD
pynigiri-0.1.5.dist-info/licenses/LICENSE
